README.md
setup.py
matrix_computation/__init__.py
matrix_computation/matrix.py
matrix_computation.egg-info/PKG-INFO
matrix_computation.egg-info/SOURCES.txt
matrix_computation.egg-info/dependency_links.txt
matrix_computation.egg-info/not-zip-safe
matrix_computation.egg-info/top_level.txt