Metadata-Version: 1.0
Name: matrix-computation
Version: 0.1
Summary: Matrix comutations
Home-page: UNKNOWN
Author: UNKNOWN
Author-email: UNKNOWN
License: UNKNOWN
Platform: UNKNOWN
